[{"id": 1001, "checked": false, "name": "Abobora Japonesa", "unit": "500g", "price": 4.5}, {"id": 1002, "checked": false, "name": "Acerola Congelada ", "unit": "500g", "price": 5.94}, {"id": 1003, "checked": false, "name": "Agriao antigo", "unit": "molho", "price": 5.0}, {"id": 1004, "checked": false, "name": "Alface americana", "unit": "unidade", "price": 5.0}, {"id": 1005, "checked": false, "name": "Alface crespa", "unit": "unidade", "price": 5.0}, {"id": 1006, "checked": false, "name": "Alface lisa", "unit": "unidade", "price": 5.0}, {"id": 1007, "checked": false, "name": "Alface romana", "unit": "unidade", "price": 5.0}, {"id": 1008, "checked": false, "name": "Alface roxa", "unit": "unidade", "price": 5.0}, {"id": 1009, "checked": false, "name": "Almeirao", "unit": "unidade", "price": 5.0}, {"id": 1010, "checked": false, "name": "Almeirao roxo", "unit": "molho", "price": 5.0}, {"id": 1011, "checked": false, "name": "Azedinha", "unit": "molho", "price": 5.0}]